README.md
setup.py
refconfig/__init__.py
refconfig/config_parser.py
refconfig/config_type.py
refconfig/jyonnie_config.py
refconfig.egg-info/PKG-INFO
refconfig.egg-info/SOURCES.txt
refconfig.egg-info/dependency_links.txt
refconfig.egg-info/requires.txt
refconfig.egg-info/top_level.txt