Metadata-Version: 2.1
Name: refconfig
Version: 0.1.2
Summary: a flexible and variable-based tool for multi-type configuration, including json, yaml, and python dict
Home-page: https://github.com/Jyonn/RefConfig
Author: Jyonn Liu
Author-email: i@6-79.cn
License: MIT Licence
Keywords: configuration,refer
Platform: any
